Flask_RESTive-0.0.3.dist-info/DESCRIPTION.rst
Flask_RESTive-0.0.3.dist-info/METADATA
Flask_RESTive-0.0.3.dist-info/RECORD
Flask_RESTive-0.0.3.dist-info/WHEEL
Flask_RESTive-0.0.3.dist-info/metadata.json
Flask_RESTive-0.0.3.dist-info/top_level.txt
flask_restive/__init__.py
flask_restive/api.py
flask_restive/exceptions.py
flask_restive/params.py
flask_restive/resources.py
flask_restive/schema_fields.py
flask_restive/schema_opts.py
flask_restive/schemas.py
flask_restive/services.py
flask_restive/types.py
flask_restive/utils.py
flask_restive_sqlalchemy/__init__.py
flask_restive_sqlalchemy/models.py
flask_restive_sqlalchemy/services.py
flask_restive_sqlalchemy/utils.py
