Metadata-Version: 2.0
Name: Flask-RESTive
Version: 0.0.3
Summary: Flask RESTive is a REST API Flask extension based on Flask-RESTful & Marshmallow.
Home-page: https://github.com/left-join/flask-restive
Author: left-join
Author-email: left-join@riseup.net
License: MIT
Download-URL: https://github.com/left-join/flask-restive.git
Keywords: flask,rest,api,flask_restful,marshmallow
Platform: a
Platform: n
Platform: y
Classifier: Environment :: Web Environment
Classifier: Intended Audience :: Developers
Classifier: License :: OSI Approved :: MIT License
Classifier: Operating System :: OS Independent
Classifier: Programming Language :: Python
Classifier: Topic :: Internet :: WWW/HTTP :: Dynamic Content
Classifier: Topic :: Software Development :: Libraries :: Python Modules
Requires-Dist: flask (>=0.12.2)
Requires-Dist: flask-restful (>=0.3.6)
Requires-Dist: marshmallow (>=3.0.0b3)
Requires-Dist: six (>=1.10.0)
